LICENSE
MANIFEST.in
VERSION
setup.py
nativo/__init__.py
nativo/api_requestor.py
nativo/auth.py
nativo/entities.py
nativo/error.py
nativo/http_client.py
nativo/metrics.py
nativo/resolutions.py
nativo/resource.py
nativo/util.py
nativo/version.py
nativo.egg-info/PKG-INFO
nativo.egg-info/SOURCES.txt
nativo.egg-info/dependency_links.txt
nativo.egg-info/requires.txt
nativo.egg-info/top_level.txt